telegram_logger_fresh/__init__.py
telegram_logger_fresh/telegram_logger_fresh.py
telegram_logger_fresh-0.1.0.dist-info/METADATA
telegram_logger_fresh-0.1.0.dist-info/WHEEL
telegram_logger_fresh-0.1.0.dist-info/top_level.txt
telegram_logger_fresh-0.1.0.dist-info/RECORD
