Metadata-Version: 2.1
Name: telegram_logger_fresh
Version: 0.1.0
Summary: A simple library to send messages to Telegram using a bot
Author: Danya
Author-email: danyanaro@gmail.com
Classifier: Programming Language :: Python :: 3
Classifier: License :: OSI Approved :: MIT License
Classifier: Operating System :: OS Independent
Requires-Python: >=3.6
Requires-Dist: requests >=2.20.0
